{
    "name": "test Extension",
    "description": "",
    "dependencies": {
        "core": "*",
        "radio": "*",
        "microphone": "*",
        "Extension": "github:kittiponghuak/extension#master"
    },
    "files": [
        "main.blocks",
        "main.ts",
        "README.md"
    ],
    "testFiles": [
        "test.ts"
    ],
    "targetVersions": {
        "target": "4.0.18",
        "targetId": "microbit"
    },
    "supportedTargets": [
        "microbit"
    ],
    "preferredEditor": "blocksprj"
}
